isaac_xml_validator.py
isaac_xml_validator-1.16.0.dist-info/licenses/LICENCE.md
isaacxmlvalidatorpipy/__init__.py
xsd/achievements.xsd
xsd/ambush.xsd
xsd/babies.xsd
xsd/backdrops.xsd
xsd/bombcostumes.xsd
xsd/bosscolors.xsd
xsd/bossoverlays.xsd
xsd/bosspools.xsd
xsd/bossportraits.xsd
xsd/challenges.xsd
xsd/costumes2.xsd
xsd/curses.xsd
xsd/cutscenes.xsd
xsd/entities2.xsd
xsd/fxlayers.xsd
xsd/giantbook.xsd
xsd/info_display.xsd
xsd/isaacTypes.xsd
xsd/itempools.xsd
xsd/items.xsd
xsd/items_metadata.xsd
xsd/locusts.xsd
xsd/metadata.xsd
xsd/minibosses.xsd
xsd/music.xsd
xsd/nightmares.xsd
xsd/playerforms.xsd
xsd/players.xsd
xsd/pocketitems.xsd
xsd/preload.xsd
xsd/recipes.xsd
xsd/shaders.xsd
xsd/sounds.xsd
xsd/stages.xsd
xsd/wisps.xsd
isaac_xml_validator-1.16.0.dist-info/METADATA
isaac_xml_validator-1.16.0.dist-info/WHEEL
isaac_xml_validator-1.16.0.dist-info/entry_points.txt
isaac_xml_validator-1.16.0.dist-info/top_level.txt
isaac_xml_validator-1.16.0.dist-info/RECORD
