Metadata-Version: 2.4
Name: isaac-xml-validator
Version: 1.16.0
Summary: A script to validate XML files for the game 'The Binding of Isaac: Repentance'
Author-email: Wofsauge <jan-.-@t-online.de>
License: MIT
Project-URL: Homepage, https://github.com/wofsauge/isaac-xml-validator
Project-URL: Bug Tracker, https://github.com/wofsauge/isaac-xml-validator/issues
Requires-Python: >=3.6
License-File: LICENCE.md
Requires-Dist: lxml
Requires-Dist: importlib-metadata
Dynamic: license-file
